datacheckerpro/__init__.py
datacheckerpro/validator.py
test/__init__.py
test/test_validator.py
datacheckerpro-0.1.dist-info/METADATA
datacheckerpro-0.1.dist-info/WHEEL
datacheckerpro-0.1.dist-info/top_level.txt
datacheckerpro-0.1.dist-info/RECORD
