Metadata-Version: 2.1
Name: datacheckerpro
Version: 0.1
Summary: A simple datavalidator for validating email, phone numbers, dates, and URLs.
Home-page: https://github.com/Data-Epic/data-validator-ogechukw-okoli
Author: Okoli Ogechukwu Abimbola
Author-email: okoliogechi74@gmail.com
Classifier: Programming Language :: Python :: 3.11
Classifier: License :: OSI Approved :: MIT License
Classifier: Operating System :: OS Independent
Requires-Python: >=3.6
